Metadata-Version: 2.1
Name: EasyTextTables
Version: 1.1.2
Summary: This package will make creating text tables easier
Home-page: https://gitbranch.ru/git/max.taran.210/TextTables
Author: Max Taran
Author-email: tmasik.t.210@mail.ru
License: MIT
Keywords: text table
Platform: UNKNOWN
License-File: LICENSE.txt
